datahub_sdk-1.0.4.dist-info/DESCRIPTION.rst
datahub_sdk-1.0.4.dist-info/METADATA
datahub_sdk-1.0.4.dist-info/RECORD
datahub_sdk-1.0.4.dist-info/WHEEL
datahub_sdk-1.0.4.dist-info/metadata.json
datahub_sdk-1.0.4.dist-info/top_level.txt
macaca/__init__.py
macaca/datahub.py
macaca/sdk.py
