Metadata-Version: 2.0
Name: datahub-sdk
Version: 1.0.4
Summary: Macaca DataHub Client
Home-page: https://github.com/macacajs/datahub-python-sdk
Author: xdf
Author-email: xudafeng@126.com
License: MIT
Keywords: data,management,continues
Platform: UNKNOWN
Classifier: Development Status :: 3 - Alpha
Classifier: Intended Audience :: Developers
Classifier: Topic :: Software Development :: Build Tools
Classifier: License :: OSI Approved :: MIT License
Classifier: Programming Language :: Python :: 2.7
Classifier: Programming Language :: Python :: 3.4
Classifier: Programming Language :: Python :: 3.5
Requires-Dist: enum34
Requires-Dist: requests
Requires-Dist: retrying
Provides-Extra: test
Requires-Dist: coverage; extra == 'test'
Requires-Dist: pytest; extra == 'test'
Requires-Dist: pytest-cov; extra == 'test'
Requires-Dist: pytest-xdist; extra == 'test'
Requires-Dist: responses; extra == 'test'
Requires-Dist: tox; extra == 'test'
